bceidaas/__init__.py
bceidaas/bce_base_client.py
bceidaas/bce_client_configuration.py
bceidaas/bce_response.py
bceidaas/compat.py
bceidaas/exception.py
bceidaas/handler.py
bceidaas/protocol.py
bceidaas/region.py
bceidaas/utils.py
bceidaas/auth/__init__.py
bceidaas/auth/bce_credentials.py
bceidaas/auth/bce_v1_signer.py
bceidaas/auth/iam_credentials.py
bceidaas/auth/idaas_credentials.py
bceidaas/cache/__init__.py
bceidaas/cache/token_cache.py
bceidaas/http/__init__.py
bceidaas/http/bce_http_client.py
bceidaas/http/handler.py
bceidaas/http/http_content_types.py
bceidaas/http/http_headers.py
bceidaas/http/http_methods.py
bceidaas/middleware/__init__.py
bceidaas/middleware/auth/__init__.py
bceidaas/middleware/auth/const.py
bceidaas/middleware/auth/iam_session.py
bceidaas/middleware/auth/idaas_session.py
bceidaas/middleware/auth/utils.py
bceidaas/retry/__init__.py
bceidaas/retry/retry_policy.py
bceidaas/services/__init__.py
bceidaas/services/iam/__init__.py
bceidaas/services/iam/iam_client.py
bceidaas/services/idaas/__init__.py
bceidaas/services/idaas/idaas_client.py
bceidaas/services/sts/__init__.py
bceidaas/services/sts/sts_client.py
bceidaas-0.0.1.dev2.dist-info/METADATA
bceidaas-0.0.1.dev2.dist-info/WHEEL
bceidaas-0.0.1.dev2.dist-info/top_level.txt
bceidaas-0.0.1.dev2.dist-info/RECORD
